streamlit_component_socket_client/__init__.py
streamlit_component_socket_client/frontend/index.html
streamlit_component_socket_client/frontend/main.js
streamlit_component_socket_client/frontend/streamlit-component-lib.js
streamlit_component_socket_client/frontend/style.css
streamlit_component_socket_client-0.1.0.dist-info/LICENSE
streamlit_component_socket_client-0.1.0.dist-info/METADATA
streamlit_component_socket_client-0.1.0.dist-info/WHEEL
streamlit_component_socket_client-0.1.0.dist-info/top_level.txt
streamlit_component_socket_client-0.1.0.dist-info/RECORD
