Metadata-Version: 2.1
Name: streamlit-component-socket-client
Version: 0.1.0
Summary: socket client which allow you to use and render session tate with out to wait for socket.
Author: Muhammad Kamran
Author-email: mkrnaqeebi@gmail.com
Requires-Python: >=3.7
License-File: LICENSE
Requires-Dist: streamlit >=1.2
Requires-Dist: jinja2
